pitchpredict/__init__.py
pitchpredict/analyze_pitch_data.py
pitchpredict/api.py
pitchpredict/cli.py
pitchpredict/fetch_pitch_data.py
pitchpredict/logger_config.py
pitchpredict/player_lookup.py
pitchpredict/similarity.py
pitchpredict/models/__init__.py
pitchpredict/models/pitch.py
pitchpredict/models/pitchpredict_config.py
pitchpredict/models/pitchpredict_response.py
pitchpredict-0.2.6.dist-info/LICENSE
pitchpredict-0.2.6.dist-info/METADATA
pitchpredict-0.2.6.dist-info/WHEEL
pitchpredict-0.2.6.dist-info/entry_points.txt
pitchpredict-0.2.6.dist-info/top_level.txt
pitchpredict-0.2.6.dist-info/RECORD
