Metadata-Version: 2.1
Name: pitchpredict
Version: 0.2.6
Summary: An open source utility for predicting what an MLB pitcher will throw in a given context
Author-email: Addison Kline <akline@baseball-analytica.com>
License: MIT License
Classifier: Programming Language :: Python :: 3
Classifier: License :: OSI Approved :: MIT License
Classifier: Operating System :: OS Independent
Requires-Python: >=3.11
License-File: LICENSE
Requires-Dist: pybaseball>=2.2.6
Requires-Dist: pydantic>=2.9.2
Requires-Dist: numpy>=2.1.2
Requires-Dist: pandas>=2.2.3
